MANIFEST.in
README.rst
setup.cfg
setup.py
bin/mata_create_project
mata/__init__.py
mata/compile_api.bat
mata/compile_api.py
mata/compile_api.sh
mata/config
mata/cythonify_api.bat
mata/cythonify_api.sh
mata/game.py
mata/icon.png
mata/launcher.py
mata/line_counter.py
mata/main.py
mata/mod.py
mata/modlist
mata/modlist_blank
mata/pythonify_api.bat
mata/pythonify_api.sh
mata/setup.bat
mata/setup.sh
mata/util.py
mata.egg-info/PKG-INFO
mata.egg-info/SOURCES.txt
mata.egg-info/dependency_links.txt
mata.egg-info/requires.txt
mata.egg-info/top_level.txt
mata/api/__init__.py
mata/api/ai.c
mata/api/ai.pyx
mata/api/audio.c
mata/api/audio.pyx
mata/api/biome.c
mata/api/biome.pyx
mata/api/cmd.c
mata/api/cmd.pyx
mata/api/colour.c
mata/api/colour.pyx
mata/api/combat.c
mata/api/combat.pyx
mata/api/dimension.c
mata/api/dimension.pyx
mata/api/entity.c
mata/api/entity.pyx
mata/api/item.c
mata/api/item.pyx
mata/api/network.c
mata/api/network.pyx
mata/api/packets.c
mata/api/packets.pyx
mata/api/properties.c
mata/api/properties.pyx
mata/api/vehicle.c
mata/api/vehicle.pyx
mata/api/gui/gui.c
mata/api/gui/gui.pyx
mata/api/gui/objects.c
mata/api/gui/objects.pyx
mata/mods/__init__.py
mata/mods/default/__init__.py
mata/mods/default/biomes.py
mata/mods/default/items.py
mata/mods/default/neural_net.py
mata/mods/default/packets.py
mata/mods/default/tiles.py
mata/mods/default/client/__init__.py
mata/mods/default/client/client_mod.py
mata/mods/default/client/events/__init__.py
mata/mods/default/client/events/other_events.py
mata/mods/default/client/events/tick_events.py
mata/mods/default/client/gui/__init__.py
mata/mods/default/client/gui/extras.py
mata/mods/default/client/gui/game_overlays.py
mata/mods/default/client/gui/game_screens.py
mata/mods/default/client/gui/menus.py
mata/mods/default/client/gui/messages.py
mata/mods/default/server/__init__.py
mata/mods/default/server/server_mod.py
mata/mods/default/server/entity/bear.py
mata/mods/default/server/entity/npc.py
mata/mods/default/server/events/events.py
mata/mods/default/server/vehicle/horse.py
mata/resources/audio/main_menu.ogg
mata/resources/font/main.ttf
