Metadata-Version: 1.0
Name: mata
Version: 0.1.3
Summary: Medieval Attack-Trade-Alliance Game Engine
Home-page: https://gitlab.com/mpbagot/mata
Author: mpbagot
Author-email: mitchell.bagot@education.nsw.gov.au
License: MIT
Keywords: engine,game,pygame
Platform: UNKNOWN
